datalakebundle/DataLakeBundle.py
datalakebundle/DataLakeBundleTest.py
datalakebundle/_config/.gitignore
datalakebundle/_config/config.yaml
datalakebundle/_config/config_test.yaml
datalakebundle/delta/DeltaStorage.py
datalakebundle/imports.py
datalakebundle/notebook/decorator/DataFrameReturningDecorator.py
datalakebundle/notebook/decorator/DuplicateColumnsChecker.py
datalakebundle/notebook/decorator/data_frame_loader.py
datalakebundle/notebook/decorator/data_frame_saver.py
datalakebundle/notebook/decorator/tests/DecoratorsTest.py
datalakebundle/notebook/decorator/tests/decorators_fixture.py
datalakebundle/notebook/decorator/tests/decorators_test.py
datalakebundle/notebook/decorator/transformation.py
datalakebundle/notebook/lineage/TableWriter.py
datalakebundle/notebook/lineage/TableWriterParser.py
datalakebundle/notebook/lineage/argument/ArgumentMapping.py
datalakebundle/notebook/lineage/argument/ReadTable.py
datalakebundle/notebook/lineage/argument/TableParams.py
datalakebundle/table/TableExistenceChecker.py
datalakebundle/table/UnknownTableException.py
datalakebundle/table/class_/table_schema_loader.py
datalakebundle/table/create/TableCreator.py
datalakebundle/table/create/TableCreatorCommand.py
datalakebundle/table/create/TableDefinition.py
datalakebundle/table/create/TableDefinitionFactory.py
datalakebundle/table/create/TableRecreator.py
datalakebundle/table/create/TableRecreatorCommand.py
datalakebundle/table/delete/TableDeleter.py
datalakebundle/table/delete/TableDeleterCommand.py
datalakebundle/table/identifier/Expression.py
datalakebundle/table/identifier/IdentifierParser.py
datalakebundle/table/identifier/ValueResolverInterface.py
datalakebundle/table/identifier/fill_template.py
datalakebundle/table/identifier/fill_template_test.py
datalakebundle/table/identifier/placeholders_extractor.py
datalakebundle/table/name/TableNameTemplateGetter.py
datalakebundle/table/name/TableNames.py
datalakebundle/table/name/TableNamesParser.py
datalake_bundle-1.3.0.dist-info/entry_points.txt
datalake_bundle-1.3.0.dist-info/LICENSE
datalake_bundle-1.3.0.dist-info/WHEEL
datalake_bundle-1.3.0.dist-info/METADATA
datalake_bundle-1.3.0.dist-info/RECORD
