Metadata-Version: 2.1
Name: datalake-bundle
Version: 1.3.0
Summary: DataLake tables management bundle for the Daipe Framework
Home-page: https://github.com/daipe-ai/datalake-bundle
License: MIT
Author: Jiri Koutny
Author-email: jiri.koutny@datasentics.com
Requires-Python: >=3.8,<4.0
Classifier: License :: OSI Approved :: MIT License
Classifier: Operating System :: OS Independent
Classifier: Programming Language :: Python :: 3
Classifier: Programming Language :: Python :: 3.8
Classifier: Programming Language :: Python :: 3.9
Requires-Dist: console-bundle (>=0.5,<0.6)
Requires-Dist: daipe-core (>=1.2,<2.0)
Requires-Dist: deepdiff (>=5,<6)
Requires-Dist: injecta (>=0.10.0,<0.11.0)
Requires-Dist: pyfony-bundles (>=0.4.0,<0.5.0)
Requires-Dist: pyspark-bundle (>=1.2,<2.0)
Requires-Dist: simpleeval (>=0.9.10,<1.0.0)
Project-URL: Repository, https://github.com/daipe-ai/datalake-bundle
